jira/__init__.py
jira/client.py
jira/exceptions.py
jira_python-0.2.4.dist-info/LICENSE
jira_python-0.2.4.dist-info/METADATA
jira_python-0.2.4.dist-info/WHEEL
jira_python-0.2.4.dist-info/RECORD
